nsip_client/__init__.py
nsip_client/cli.py
nsip_client/client.py
nsip_client/exceptions.py
nsip_client/models.py
nsip_client-1.4.7.dist-info/METADATA
nsip_client-1.4.7.dist-info/WHEEL
nsip_client-1.4.7.dist-info/entry_points.txt
nsip_client-1.4.7.dist-info/RECORD
